chainge/__init__.py
chainge/api/api.py
chainge/chain/tools/fundamentals.py
chainge/chain/tools/utils.py
chainge/config.py
chainge-0.0.1.4.dist-info/LICENSE
chainge-0.0.1.4.dist-info/METADATA
chainge-0.0.1.4.dist-info/WHEEL
chainge-0.0.1.4.dist-info/RECORD
