Metadata-Version: 2.1
Name: chainge
Version: 0.0.1.4
Summary: A comprehensive set of LangChain AI tools to help your AI agents interact with and thrive in moneyland.
License: MIT
Keywords: large language models,AI,LLM
Author: AnshKetchum
Author-email: eye.am.ansh@gmail.com
Requires-Python: >=3.10,<4.0
Classifier: License :: OSI Approved :: MIT License
Classifier: Operating System :: OS Independent
Classifier: Programming Language :: Python :: 3
Classifier: Programming Language :: Python :: 3.10
Classifier: Programming Language :: Python :: 3.11
Classifier: Programming Language :: Python :: 3.12
Requires-Dist: langchain (>=0.0.325,<0.0.326)
Requires-Dist: requests (>=2.31.0,<3.0.0)
Requires-Dist: urllib3 (>=2.0.7,<3.0.0)
